myproject/__init__.py
myproject/main.py
myproject/merkle_proof.py
myproject/util.py
xichengtong_rekor-3.0.dist-info/entry_points.txt
xichengtong_rekor-3.0.dist-info/LICENSE.md
xichengtong_rekor-3.0.dist-info/METADATA
xichengtong_rekor-3.0.dist-info/WHEEL
xichengtong_rekor-3.0.dist-info/RECORD
