Metadata-Version: 2.1
Name: xichengtong-rekor
Version: 3.0
Summary: A Python project for secure artifact management
License: MIT
Author: XichengTong
Author-email: xt2226@nyu.edu
Requires-Python: >=3.12,<4.0
Classifier: License :: OSI Approved :: MIT License
Classifier: Programming Language :: Python :: 3
Classifier: Programming Language :: Python :: 3.12
Classifier: Programming Language :: Python :: 3.13
Requires-Dist: cryptography (>=43.0.3,<44.0.0)
Requires-Dist: requests (>=2.32.3,<3.0.0)
Requires-Dist: sigstore-rekor-types (>=0.0.13,<0.0.14)
